runabq/__init__.py
runabq/args.py
runabq/command.py
runabq/core.py
runabq/files.py
runabq-1.0.2.dist-info/LICENCE.md
runabq-1.0.2.dist-info/METADATA
runabq-1.0.2.dist-info/WHEEL
runabq-1.0.2.dist-info/entry_points.txt
runabq-1.0.2.dist-info/top_level.txt
runabq-1.0.2.dist-info/RECORD
