Metadata-Version: 2.1
Name: runabq
Version: 1.0.2
Summary: runabq is a command tool that can execute multiple input data files of FEA software Abaqus in succession.
Home-page: https://github.com/simulation-lab/runabq
Author: kino
Author-email: simulation.space.labs@gmail.com
License: UNKNOWN
Platform: UNKNOWN
Classifier: License :: OSI Approved :: MIT License
Classifier: Programming Language :: Python :: 3
Classifier: Programming Language :: Python :: 3.8
Classifier: Programming Language :: Python :: 3.9
Classifier: Programming Language :: Python :: 3.10
Classifier: Operating System :: OS Independent
Requires-Python: ~=3.8
License-File: LICENCE.md
Requires-Dist: click (~=7.1)
